README.md
setup.py
sshxx.egg-info/PKG-INFO
sshxx.egg-info/SOURCES.txt
sshxx.egg-info/dependency_links.txt
sshxx.egg-info/entry_points.txt
sshxx.egg-info/requires.txt
sshxx.egg-info/top_level.txt
yssh/__init__.py
yssh/__main__.py
yssh/yssh.py