Metadata-Version: 2.1
Name: sshxx
Version: 1.0.1
Summary: run command/script on remote hosts.
Home-page: https://github.com/walkerever/yssh
Author: Yonghang Wang
Author-email: wyhang@gmail.com
License: Apache 2
Keywords: ssh
Platform: UNKNOWN
Classifier: License :: OSI Approved :: Apache Software License
